[
    {
        "_id":1,
        "name":"Ishtiuq Ahmed",
        "projectName":"Virtual Bd"
    },
    {
        "_id":2,
        "name":"Ishtiuq Ahmed",
        "projectName":"Virtual Bd"
    },
    {
        "_id":3,
        "name":"Ishtiuq Ahmed",
        "projectName":"Virtual Bd"
    },
    {
        "_id":4,
        "name":"Ishtiuq Ahmed",
        "projectName":"Virtual Bd"
    },
    {
        "_id":5,
        "name":"Ishtiuq Ahmed",
        "projectName":"Virtual Bd"
    },
    {
        "_id":6,
        "name":"Ishtiuq Ahmed",
        "projectName":"Virtual Bd"
    },
    {
        "_id":7,
        "name":"Ishtiuq Ahmed",
        "projectName":"Virtual Bd"
    }
]